chatosaurus_api-0.1.0.dist-info/licenses/LICENSE
llm_providers/__init__.py
llm_providers/base_provider.py
llm_providers/factory.py
llm_providers/openai.py
chatosaurus_api-0.1.0.dist-info/METADATA
chatosaurus_api-0.1.0.dist-info/WHEEL
chatosaurus_api-0.1.0.dist-info/entry_points.txt
chatosaurus_api-0.1.0.dist-info/top_level.txt
chatosaurus_api-0.1.0.dist-info/RECORD
